twitchat/__init__.py
twitchat/comm_template.py
twitchat/commands.py
twitchat/duckduckgo_abstract.py
twitchat/files_to_copy.json
twitchat/get_user_info.py
twitchat/permissions.json
twitchat/permissions.py
twitchat/settings.py
twitchat/test_classes.py
twitchat/timers.json
twitchat/timers.py
twitchat/twitchbot.py
twitchat-1.4.3.dist-info/entry_points.txt
twitchat-1.4.3.dist-info/LICENSE
twitchat-1.4.3.dist-info/WHEEL
twitchat-1.4.3.dist-info/METADATA
twitchat-1.4.3.dist-info/RECORD
